Metadata-Version: 2.1
Name: kartik-talwar-102003475
Version: 1.2.1
Summary: Topsis Calculation Package
Author: Kartik Talwar
Author-email: <ktalwar_be20@thapar.edu>
Keywords: python,topsis,mcdm
Classifier: Development Status :: 1 - Planning
Classifier: Intended Audience :: Developers
Classifier: Programming Language :: Python :: 3
Classifier: Operating System :: Unix
Classifier: Operating System :: MacOS :: MacOS X
Classifier: Operating System :: Microsoft :: Windows
